mugit/__init__.py
mugit/add.py
mugit/main.py
mugit/manifest.py
mugit/pull.py
mugit/release.py
mugit/remove.py
mugit/rename.py
mugit/repository.py
mugit/select.py
mugit/status.py
mugit/update.py
mugit-1.1.1.dist-info/LICENSE.txt
mugit-1.1.1.dist-info/METADATA
mugit-1.1.1.dist-info/WHEEL
mugit-1.1.1.dist-info/entry_points.txt
mugit-1.1.1.dist-info/top_level.txt
mugit-1.1.1.dist-info/RECORD
