Metadata-Version: 2.1
Name: mugit
Version: 1.1.1
Summary: Git multi-repository workspace management tool
Home-page: https://bitbucket.org/digitalstirling/mugit
Author: Richard Walters
Author-email: rwalters@digitalstirling.com
License: MIT
Keywords: git
Platform: UNKNOWN
Classifier: Development Status :: 3 - Alpha
Classifier: Intended Audience :: Developers
Classifier: Topic :: Software Development :: Version Control :: Git
Classifier: License :: OSI Approved :: MIT License
Classifier: Programming Language :: Python :: 2.7
Classifier: Programming Language :: Python :: 3
Requires-Python: >=2.7, <4
